README.md
setup.cfg
setup.py
pynumbat/__init__.py
pynumbat/__main__.py
pynumbat/commands.py
pynumbat/common.py
pynumbat/decorators.py
pynumbat/exceptions.py
pynumbat.egg-info/PKG-INFO
pynumbat.egg-info/SOURCES.txt
pynumbat.egg-info/dependency_links.txt
pynumbat.egg-info/entry_points.txt
pynumbat.egg-info/requires.txt
pynumbat.egg-info/top_level.txt