Metadata-Version: 2.1
Name: pynumbat
Version: 0.1.10
Summary: Python generator project
Home-page: https://github.com/eduardogpg/pygenerate
Author: Eduardo Ismael Garcia Perez
Author-email: eduardo78d@gmail.com
License: MIT
Keywords: Python Generate,Generate,Project
Platform: UNKNOWN
Classifier: Development Status :: 3 - Alpha
Classifier: Intended Audience :: Developers
Classifier: License :: OSI Approved :: MIT License
Classifier: Programming Language :: Python :: 3
